[{"timestamp": "2016-08-29T00:00:00+00:00", "value": "30.75"}, {"timestamp": "2016-08-29T01:00:00+00:00", "value": "30.52"}, {"timestamp": "2016-08-29T02:00:00+00:00", "value": "30.53"}, {"timestamp": "2016-08-29T03:00:00+00:00", "value": "30.82"}, {"timestamp": "2016-08-29T04:00:00+00:00", "value": "36.96"}, {"timestamp": "2016-08-29T05:00:00+00:00", "value": "40.26"}, {"timestamp": "2016-08-29T06:00:00+00:00", "value": "41"}, {"timestamp": "2016-08-29T07:00:00+00:00", "value": "34"}, {"timestamp": "2016-08-29T08:00:00+00:00", "value": "33"}, {"timestamp": "2016-08-29T09:00:00+00:00", "value": "33"}, {"timestamp": "2016-08-29T10:00:00+00:00", "value": "33"}, {"timestamp": "2016-08-29T11:00:00+00:00", "value": "33"}, {"timestamp": "2016-08-29T12:00:00+00:00", "value": "33"}, {"timestamp": "2016-08-29T13:00:00+00:00", "value": "33"}, {"timestamp": "2016-08-29T14:00:00+00:00", "value": "40"}, {"timestamp": "2016-08-29T15:00:00+00:00", "value": "41"}, {"timestamp": "2016-08-29T16:00:00+00:00", "value": "41"}, {"timestamp": "2016-08-29T17:00:00+00:00", "value": "41"}, {"timestamp": "2016-08-29T18:00:00+00:00", "value": "50.5"}, {"timestamp": "2016-08-29T19:00:00+00:00", "value": "43"}, {"timestamp": "2016-08-29T20:00:00+00:00", "value": "42"}, {"timestamp": "2016-08-29T21:00:00+00:00", "value": "40"}, {"timestamp": "2016-08-29T22:00:00+00:00", "value": "37.64"}, {"timestamp": "2016-08-29T23:00:00+00:00", "value": "33.73"}]