[{"timestamp": "2019-02-20T00:00:00+00:00", "value": "53.99"}, {"timestamp": "2019-02-20T01:00:00+00:00", "value": "49"}, {"timestamp": "2019-02-20T02:00:00+00:00", "value": "51.91"}, {"timestamp": "2019-02-20T03:00:00+00:00", "value": "51.91"}, {"timestamp": "2019-02-20T04:00:00+00:00", "value": "54.33"}, {"timestamp": "2019-02-20T05:00:00+00:00", "value": "63.1"}, {"timestamp": "2019-02-20T06:00:00+00:00", "value": "63"}, {"timestamp": "2019-02-20T07:00:00+00:00", "value": "63.12"}, {"timestamp": "2019-02-20T08:00:00+00:00", "value": "61.65"}, {"timestamp": "2019-02-20T09:00:00+00:00", "value": "57.97"}, {"timestamp": "2019-02-20T10:00:00+00:00", "value": "54.46"}, {"timestamp": "2019-02-20T11:00:00+00:00", "value": "50.92"}, {"timestamp": "2019-02-20T12:00:00+00:00", "value": "50"}, {"timestamp": "2019-02-20T13:00:00+00:00", "value": "54.46"}, {"timestamp": "2019-02-20T14:00:00+00:00", "value": "55.66"}, {"timestamp": "2019-02-20T15:00:00+00:00", "value": "63"}, {"timestamp": "2019-02-20T16:00:00+00:00", "value": "67"}, {"timestamp": "2019-02-20T17:00:00+00:00", "value": "76.42"}, {"timestamp": "2019-02-20T18:00:00+00:00", "value": "75"}, {"timestamp": "2019-02-20T19:00:00+00:00", "value": "65"}, {"timestamp": "2019-02-20T20:00:00+00:00", "value": "60.01"}, {"timestamp": "2019-02-20T21:00:00+00:00", "value": "57.55"}, {"timestamp": "2019-02-20T22:00:00+00:00", "value": "53.85"}, {"timestamp": "2019-02-20T23:00:00+00:00", "value": "59.33"}]