[{"timestamp": "2019-10-26T00:00:00+00:00", "value": "32.93"}, {"timestamp": "2019-10-26T01:00:00+00:00", "value": "32.6"}, {"timestamp": "2019-10-26T02:00:00+00:00", "value": "32.88"}, {"timestamp": "2019-10-26T03:00:00+00:00", "value": "32.88"}, {"timestamp": "2019-10-26T04:00:00+00:00", "value": "40"}, {"timestamp": "2019-10-26T05:00:00+00:00", "value": "45.68"}, {"timestamp": "2019-10-26T06:00:00+00:00", "value": "58.2"}, {"timestamp": "2019-10-26T07:00:00+00:00", "value": "54.32"}, {"timestamp": "2019-10-26T08:00:00+00:00", "value": "43.38"}, {"timestamp": "2019-10-26T09:00:00+00:00", "value": "40"}, {"timestamp": "2019-10-26T10:00:00+00:00", "value": "39"}, {"timestamp": "2019-10-26T11:00:00+00:00", "value": "31.13"}, {"timestamp": "2019-10-26T12:00:00+00:00", "value": "31.13"}, {"timestamp": "2019-10-26T13:00:00+00:00", "value": "39"}, {"timestamp": "2019-10-26T14:00:00+00:00", "value": "40"}, {"timestamp": "2019-10-26T15:00:00+00:00", "value": "48.87"}, {"timestamp": "2019-10-26T16:00:00+00:00", "value": "62.75"}, {"timestamp": "2019-10-26T17:00:00+00:00", "value": "68.05"}, {"timestamp": "2019-10-26T18:00:00+00:00", "value": "57.17"}, {"timestamp": "2019-10-26T19:00:00+00:00", "value": "43.9"}, {"timestamp": "2019-10-26T20:00:00+00:00", "value": "38"}, {"timestamp": "2019-10-26T21:00:00+00:00", "value": "37.69"}, {"timestamp": "2019-10-26T22:00:00+00:00", "value": "37.59"}, {"timestamp": "2019-10-26T23:00:00+00:00", "value": "36.64"}]