[{"timestamp": "2024-06-02T00:00:00+00:00", "value": "48.61"}, {"timestamp": "2024-06-02T01:00:00+00:00", "value": "44.3"}, {"timestamp": "2024-06-02T02:00:00+00:00", "value": "8.32"}, {"timestamp": "2024-06-02T03:00:00+00:00", "value": "4.39"}, {"timestamp": "2024-06-02T04:00:00+00:00", "value": "4.9"}, {"timestamp": "2024-06-02T05:00:00+00:00", "value": "4.11"}, {"timestamp": "2024-06-02T06:00:00+00:00", "value": "0.97"}, {"timestamp": "2024-06-02T07:00:00+00:00", "value": "0"}, {"timestamp": "2024-06-02T08:00:00+00:00", "value": "1.28"}, {"timestamp": "2024-06-02T09:00:00+00:00", "value": "0.24"}, {"timestamp": "2024-06-02T10:00:00+00:00", "value": "-0.72"}, {"timestamp": "2024-06-02T11:00:00+00:00", "value": "-5.91"}, {"timestamp": "2024-06-02T12:00:00+00:00", "value": "-18.92"}, {"timestamp": "2024-06-02T13:00:00+00:00", "value": "-20.71"}, {"timestamp": "2024-06-02T14:00:00+00:00", "value": "-5.74"}, {"timestamp": "2024-06-02T15:00:00+00:00", "value": "3.03"}, {"timestamp": "2024-06-02T16:00:00+00:00", "value": "60.12"}, {"timestamp": "2024-06-02T17:00:00+00:00", "value": "96.3"}, {"timestamp": "2024-06-02T18:00:00+00:00", "value": "137.26"}, {"timestamp": "2024-06-02T19:00:00+00:00", "value": "117.06"}, {"timestamp": "2024-06-02T20:00:00+00:00", "value": "103.67"}, {"timestamp": "2024-06-02T21:00:00+00:00", "value": "92.41"}, {"timestamp": "2024-06-02T22:00:00+00:00", "value": "93.51"}, {"timestamp": "2024-06-02T23:00:00+00:00", "value": "88.61"}]