[{"timestamp": "2024-08-15T19:00:00+00:00", "value": "4.18"}, {"timestamp": "2024-08-15T21:00:00+00:00", "value": "-0.07"}, {"timestamp": "2024-08-15T09:00:00+00:00", "value": "15.18"}, {"timestamp": "2024-08-15T16:00:00+00:00", "value": "11.76"}, {"timestamp": "2024-08-15T01:00:00+00:00", "value": "3.90"}, {"timestamp": "2024-08-15T12:00:00+00:00", "value": "3.18"}, {"timestamp": "2024-08-15T05:00:00+00:00", "value": "15.27"}, {"timestamp": "2024-08-15T02:00:00+00:00", "value": "4.12"}, {"timestamp": "2024-08-15T04:00:00+00:00", "value": "9.19"}, {"timestamp": "2024-08-15T22:00:00+00:00", "value": "-0.01"}, {"timestamp": "2024-08-15T13:00:00+00:00", "value": "4.36"}, {"timestamp": "2024-08-15T15:00:00+00:00", "value": "12.14"}, {"timestamp": "2024-08-15T20:00:00+00:00", "value": "1.82"}, {"timestamp": "2024-08-15T07:00:00+00:00", "value": "19.94"}, {"timestamp": "2024-08-15T14:00:00+00:00", "value": "12.27"}, {"timestamp": "2024-08-15T11:00:00+00:00", "value": "4.19"}, {"timestamp": "2024-08-15T08:00:00+00:00", "value": "19.03"}, {"timestamp": "2024-08-15T06:00:00+00:00", "value": "19.96"}, {"timestamp": "2024-08-15T03:00:00+00:00", "value": "7.00"}, {"timestamp": "2024-08-15T17:00:00+00:00", "value": "8.95"}, {"timestamp": "2024-08-15T18:00:00+00:00", "value": "5.04"}, {"timestamp": "2024-08-15T00:00:00+00:00", "value": "4.20"}, {"timestamp": "2024-08-15T23:00:00+00:00", "value": "-0.11"}, {"timestamp": "2024-08-15T10:00:00+00:00", "value": "9.86"}]