[{"timestamp": "2025-01-19T00:00:00+00:00", "value": "6.35"}, {"timestamp": "2025-01-19T16:00:00+00:00", "value": "2.93"}, {"timestamp": "2025-01-19T20:00:00+00:00", "value": "4.43"}, {"timestamp": "2025-01-19T11:00:00+00:00", "value": "2.06"}, {"timestamp": "2025-01-19T13:00:00+00:00", "value": "2.22"}, {"timestamp": "2025-01-19T06:00:00+00:00", "value": "3.35"}, {"timestamp": "2025-01-19T18:00:00+00:00", "value": "3.29"}, {"timestamp": "2025-01-19T22:00:00+00:00", "value": "5.16"}, {"timestamp": "2025-01-19T01:00:00+00:00", "value": "4.99"}, {"timestamp": "2025-01-19T03:00:00+00:00", "value": "4.13"}, {"timestamp": "2025-01-19T02:00:00+00:00", "value": "4.17"}, {"timestamp": "2025-01-19T12:00:00+00:00", "value": "2.08"}, {"timestamp": "2025-01-19T21:00:00+00:00", "value": "4.92"}, {"timestamp": "2025-01-19T08:00:00+00:00", "value": "3.03"}, {"timestamp": "2025-01-19T17:00:00+00:00", "value": "3.1"}, {"timestamp": "2025-01-19T15:00:00+00:00", "value": "2.23"}, {"timestamp": "2025-01-19T19:00:00+00:00", "value": "3.43"}, {"timestamp": "2025-01-19T07:00:00+00:00", "value": "3.2"}, {"timestamp": "2025-01-19T10:00:00+00:00", "value": "2.74"}, {"timestamp": "2025-01-19T09:00:00+00:00", "value": "2.97"}, {"timestamp": "2025-01-19T14:00:00+00:00", "value": "2.26"}, {"timestamp": "2025-01-19T04:00:00+00:00", "value": "3.65"}, {"timestamp": "2025-01-19T05:00:00+00:00", "value": "3.51"}, {"timestamp": "2025-01-19T23:00:00+00:00", "value": "9.45"}]